llamapay/__init__.py
llamapay/constants.py
llamapay/exceptions.py
llamapay/llamapay.py
llamapay/manifest.json
llamapay/py.typed
llamapay/version.py
llamapay-0.1.0.dist-info/LICENSE
llamapay-0.1.0.dist-info/METADATA
llamapay-0.1.0.dist-info/WHEEL
llamapay-0.1.0.dist-info/top_level.txt
llamapay-0.1.0.dist-info/RECORD
